auth_satvadev/__init__.py
auth_satvadev/api/__init__.py
auth_satvadev/api/exceptions.py
auth_satvadev/api/serializers.py
auth_satvadev/api/swagger_schemas.py
auth_satvadev/api/urls.py
auth_satvadev/api/views.py
auth_satvadev/apps.py
auth_satvadev/mail.py
auth_satvadev/migrations/0001_initial.py
auth_satvadev/migrations/__init__.py
auth_satvadev/models.py
auth_satvadev/senders.py
auth_satvadev-1.0.5.dist-info/METADATA
auth_satvadev-1.0.5.dist-info/WHEEL
auth_satvadev-1.0.5.dist-info/licenses/LICENSE
auth_satvadev-1.0.5.dist-info/RECORD
